{
  "id": "linear-regression-mse-stepper",
  "type": "two-column",
  "content": {
    "pt-br": {
      "title": "Regressão Linear: calculando o MSE com dados reais",
      "body": "Agora o MSE deixa de ser definição abstrata e vira conta com dados reais.\n\n1. **Dataset usado:** `(160, 20, 55)`, `(165, 24, 59)`, `(170, 28, 64)`, `(175, 32, 68)`, `(180, 36, 72)`.\n\n2. **Entradas e saída:** altura e idade entram; `y` guarda o peso real e `ŷ` guarda a previsão.\n\n3. **Modelo de exemplo:** para fechar a conta manualmente, vamos usar `ŷ = β₀ + β₁ * altura + β₂ * idade`, com `β₀ = -21`, `β₁ = 0.4` e `β₂ = 0.6` escolhidos para este exemplo didático.\n\n4. **Objetivo da conta:** calcular erro, elevar ao quadrado, somar tudo e dividir pelo total de exemplos.\n\n> Quando cada linha do dataset entra na conta, o MSE deixa de ser sigla e vira um número verificável. Aqui o foco é validar a mecânica da conta, não mostrar o resultado do treino.\n\n---"
    },
    "en-us": {
      "title": "Linear Regression: calculating MSE with real data",
      "body": "Now MSE stops being an abstract definition and becomes arithmetic with real data.\n\n1. **Dataset used:** `(160, 20, 55)`, `(165, 24, 59)`, `(170, 28, 64)`, `(175, 32, 68)`, `(180, 36, 72)`.\n\n2. **Inputs and output:** height and age go in; `y` stores the real weight and `ŷ` stores the prediction.\n\n3. **Example model:** to close the arithmetic by hand, we will use `ŷ = β₀ + β₁ * height + β₂ * age`, with `β₀ = -21`, `β₁ = 0.4`, and `β₂ = 0.6` chosen for this teaching example.\n\n4. **Goal of the calculation:** compute the error, square it, add everything, and divide by the total number of examples.\n\n> When each dataset row enters the arithmetic, MSE stops being an acronym and becomes a verifiable number. The goal here is to validate the mechanics of the calculation, not to show training output.\n\n---"
    }
  },
  "visual": {
    "id": "progress-stepper",
    "copy": {
      "pt-br": {
        "eyebrow": "Revisão guiada",
        "title": "MSE com altura, idade e peso reais",
        "description": "Usando o mesmo dataset do slide de Python, vamos abrir a conta do MSE passo a passo com previsões numéricas.",
        "progressLabel": "Passo",
        "previousLabel": "Anterior",
        "nextLabel": "Próximo",
        "completionLabel": "Fechamento do raciocínio",
        "completionDescription": "Com esse exemplo, o MSE do conjunto fica `0.12`. No próximo slide, essa mesma sequência aparece em Python como função e loop.",
        "footer": "Aqui a conta fecha de ponta a ponta: prever peso, medir erro, elevar ao quadrado, somar e dividir por 5.",
        "table": {
          "title": "Dataset e resultados do exemplo",
          "headers": {
            "height": "Altura",
            "age": "Idade",
            "realWeight": "Peso real",
            "predictedWeight": "Previsto",
            "error": "Erro",
            "squaredError": "Erro²"
          },
          "rows": [
            {
              "height": "160",
              "age": "20",
              "realWeight": "55",
              "predictedWeight": "55.0",
              "error": "0.0",
              "squaredError": "0.00"
            },
            {
              "height": "165",
              "age": "24",
              "realWeight": "59",
              "predictedWeight": "59.4",
              "error": "0.4",
              "squaredError": "0.16"
            },
            {
              "height": "170",
              "age": "28",
              "realWeight": "64",
              "predictedWeight": "63.8",
              "error": "-0.2",
              "squaredError": "0.04"
            },
            {
              "height": "175",
              "age": "32",
              "realWeight": "68",
              "predictedWeight": "68.2",
              "error": "0.2",
              "squaredError": "0.04"
            },
            {
              "height": "180",
              "age": "36",
              "realWeight": "72",
              "predictedWeight": "72.6",
              "error": "0.6",
              "squaredError": "0.36"
            }
          ]
        },
        "steps": [
          {
            "label": "Linha 1",
            "title": "Preveja o peso do primeiro exemplo",
            "description": "Para `(altura=160, idade=20, peso=55)`, a fórmula gera `ŷ = -21 + 0.4 * 160 + 0.6 * 20 = -21 + 64 + 12 = 55`. O peso previsto bate exatamente com o peso real.",
            "formula": "ŷ = -21 + 0.4*160 + 0.6*20 = 55",
            "accent": "#00e5ff",
            "highlightedRowIndexes": [
              0
            ]
          },
          {
            "label": "Linha 2",
            "title": "Calcule o erro do segundo exemplo",
            "description": "Para `(165, 24, 59)`, a previsão fica `ŷ = -21 + 0.4 * 165 + 0.6 * 24 = 59.4`. O erro é `ŷ - y = 59.4 - 59 = 0.4`.",
            "formula": "erro = ŷ - y = 59.4 - 59 = 0.4",
            "accent": "#ff2e97",
            "highlightedRowIndexes": [
              1
            ]
          },
          {
            "label": "Quadrados",
            "title": "Eleve os erros ao quadrado",
            "description": "Os cinco erros do conjunto ficam `0`, `0.4`, `-0.2`, `0.2` e `0.6`. Ao quadrado, eles viram `0`, `0.16`, `0.04`, `0.04` e `0.36`.",
            "formula": "0² + 0.4² + (-0.2)² + 0.2² + 0.6²",
            "accent": "#fbbf24",
            "highlightedRowIndexes": [
              0,
              1,
              2,
              3,
              4
            ]
          },
          {
            "label": "Soma",
            "title": "Some todos os erros quadráticos",
            "description": "Agora juntamos as contribuições do dataset inteiro: `0 + 0.16 + 0.04 + 0.04 + 0.36 = 0.60`.",
            "formula": "soma = 0.60",
            "accent": "#a855f7",
            "highlightedRowIndexes": [
              0,
              1,
              2,
              3,
              4
            ]
          },
          {
            "label": "MSE final",
            "title": "Divida pela quantidade de exemplos",
            "description": "Como temos `5` linhas no dataset, o erro médio ao quadrado fica `0.60 / 5 = 0.12`. Esse é o custo que o treino tenta reduzir.",
            "formula": "MSE = 0.60 / 5 = 0.12",
            "accent": "#34d399",
            "highlightedRowIndexes": [
              0,
              1,
              2,
              3,
              4
            ]
          }
        ]
      },
      "en-us": {
        "eyebrow": "Guided review",
        "title": "MSE with real height, age, and weight",
        "description": "Using the same dataset from the Python slide, we now open the MSE calculation step by step with numeric predictions.",
        "progressLabel": "Step",
        "previousLabel": "Previous",
        "nextLabel": "Next",
        "completionLabel": "Reasoning complete",
        "completionDescription": "With this example, the dataset MSE becomes `0.12`. In the next slide, the same sequence appears in Python as a function and a loop.",
        "footer": "This closes the arithmetic from end to end: predict weight, measure error, square it, add everything, and divide by 5.",
        "table": {
          "title": "Dataset and example results",
          "headers": {
            "height": "Height",
            "age": "Age",
            "realWeight": "Real weight",
            "predictedWeight": "Predicted",
            "error": "Error",
            "squaredError": "Error²"
          },
          "rows": [
            {
              "height": "160",
              "age": "20",
              "realWeight": "55",
              "predictedWeight": "55.0",
              "error": "0.0",
              "squaredError": "0.00"
            },
            {
              "height": "165",
              "age": "24",
              "realWeight": "59",
              "predictedWeight": "59.4",
              "error": "0.4",
              "squaredError": "0.16"
            },
            {
              "height": "170",
              "age": "28",
              "realWeight": "64",
              "predictedWeight": "63.8",
              "error": "-0.2",
              "squaredError": "0.04"
            },
            {
              "height": "175",
              "age": "32",
              "realWeight": "68",
              "predictedWeight": "68.2",
              "error": "0.2",
              "squaredError": "0.04"
            },
            {
              "height": "180",
              "age": "36",
              "realWeight": "72",
              "predictedWeight": "72.6",
              "error": "0.6",
              "squaredError": "0.36"
            }
          ]
        },
        "steps": [
          {
            "label": "Row 1",
            "title": "Predict the first example",
            "description": "For `(height=160, age=20, weight=55)`, the formula gives `ŷ = -21 + 0.4 * 160 + 0.6 * 20 = -21 + 64 + 12 = 55`. The predicted weight matches the real weight exactly.",
            "formula": "ŷ = -21 + 0.4*160 + 0.6*20 = 55",
            "accent": "#00e5ff",
            "highlightedRowIndexes": [
              0
            ]
          },
          {
            "label": "Row 2",
            "title": "Compute the second error",
            "description": "For `(165, 24, 59)`, the prediction becomes `ŷ = -21 + 0.4 * 165 + 0.6 * 24 = 59.4`. The error is `ŷ - y = 59.4 - 59 = 0.4`.",
            "formula": "error = ŷ - y = 59.4 - 59 = 0.4",
            "accent": "#ff2e97",
            "highlightedRowIndexes": [
              1
            ]
          },
          {
            "label": "Squares",
            "title": "Square the errors",
            "description": "The five dataset errors become `0`, `0.4`, `-0.2`, `0.2`, and `0.6`. Squared, they turn into `0`, `0.16`, `0.04`, `0.04`, and `0.36`.",
            "formula": "0² + 0.4² + (-0.2)² + 0.2² + 0.6²",
            "accent": "#fbbf24",
            "highlightedRowIndexes": [
              0,
              1,
              2,
              3,
              4
            ]
          },
          {
            "label": "Sum",
            "title": "Add all squared errors",
            "description": "Now we aggregate the contribution of the whole dataset: `0 + 0.16 + 0.04 + 0.04 + 0.36 = 0.60`.",
            "formula": "sum = 0.60",
            "accent": "#a855f7",
            "highlightedRowIndexes": [
              0,
              1,
              2,
              3,
              4
            ]
          },
          {
            "label": "Final MSE",
            "title": "Divide by the number of examples",
            "description": "Since the dataset has `5` rows, the mean squared error becomes `0.60 / 5 = 0.12`. That is the cost training tries to reduce.",
            "formula": "MSE = 0.60 / 5 = 0.12",
            "accent": "#34d399",
            "highlightedRowIndexes": [
              0,
              1,
              2,
              3,
              4
            ]
          }
        ]
      }
    }
  }
}
